{
  "decks": [
    {
      "id": 1,
      "name": "JavaScript Basics",
      "description": "Core JavaScript concepts"
    },
    {
      "id": 2,
      "name": "SQL Fundamentals",
      "description": "Writing database queries"
    },
    {
      "id": 3,
      "name": "HTML & CSS",
      "description": "Building web pages"
    }
  ],
  "cards": [
    {
      "id": 1,
      "question": "What is a variable?",
      "answer": "A named container for storing data values",
      "learned": true,
      "deckId": 1
    },
    {
      "id": 2,
      "question": "What does `const` mean?",
      "answer": "Declares a variable that cannot be reassigned",
      "learned": false,
      "deckId": 1
    },
    {
      "id": 3,
      "question": "What is an array?",
      "answer": "An ordered list of values",
      "learned": true,
      "deckId": 1
    },
    {
      "id": 4,
      "question": "What does `===` do?",
      "answer": "Checks for strict equality (value AND type)",
      "learned": false,
      "deckId": 1
    },
    {
      "id": 5,
      "question": "What is SELECT used for?",
      "answer": "Retrieving data from a database table",
      "learned": false,
      "deckId": 2
    },
    {
      "id": 6,
      "question": "What is a PRIMARY KEY?",
      "answer": "A unique identifier for each row in a table",
      "learned": false,
      "deckId": 2
    },
    {
      "id": 7,
      "question": "What does WHERE do?",
      "answer": "Filters rows in a query based on a condition",
      "learned": true,
      "deckId": 2
    },
    {
      "id": 8,
      "question": "What is a FOREIGN KEY?",
      "answer": "A column that links to the primary key of another table",
      "learned": false,
      "deckId": 2
    },
    {
      "id": 9,
      "question": "What does a <div> do?",
      "answer": "Creates a block-level container element",
      "learned": false,
      "deckId": 3
    },
    {
      "id": 10,
      "question": "What is the CSS box model?",
      "answer": "Every element is a box with content, padding, border, and margin",
      "learned": false,
      "deckId": 3
    }
  ]
}